AUTHORS
CHANGELOG
CONTRIBUTING.rst
LICENSE
MANIFEST.in
README.rst
VERSION
setup.py
cruds_adminlte/__init__.py
cruds_adminlte/crud.py
cruds_adminlte/filter.py
cruds_adminlte/inline_crud.py
cruds_adminlte/models.py
cruds_adminlte/urls.py
cruds_adminlte/utils.py
cruds_adminlte/views.py
cruds_adminlte/widgets.py
cruds_adminlte/static/.DS_Store
cruds_adminlte/static/admin-lte/dist/css/AdminLTE.css
cruds_adminlte/static/admin-lte/dist/css/AdminLTE.min.css
cruds_adminlte/static/admin-lte/dist/css/skins/_all-skins.css
cruds_adminlte/static/admin-lte/dist/css/skins/_all-skins.min.css
cruds_adminlte/static/admin-lte/dist/css/skins/skin-black-light.css
cruds_adminlte/static/admin-lte/dist/css/skins/skin-black-light.min.css
cruds_adminlte/static/admin-lte/dist/css/skins/skin-black.css
cruds_adminlte/static/admin-lte/dist/css/skins/skin-black.min.css
cruds_adminlte/static/admin-lte/dist/css/skins/skin-blue-light.css
cruds_adminlte/static/admin-lte/dist/css/skins/skin-blue-light.min.css
cruds_adminlte/static/admin-lte/dist/css/skins/skin-blue.css
cruds_adminlte/static/admin-lte/dist/css/skins/skin-blue.min.css
cruds_adminlte/static/admin-lte/dist/css/skins/skin-green-light.css
cruds_adminlte/static/admin-lte/dist/css/skins/skin-green-light.min.css
cruds_adminlte/static/admin-lte/dist/css/skins/skin-green.css
cruds_adminlte/static/admin-lte/dist/css/skins/skin-green.min.css
cruds_adminlte/static/admin-lte/dist/css/skins/skin-purple-light.css
cruds_adminlte/static/admin-lte/dist/css/skins/skin-purple-light.min.css
cruds_adminlte/static/admin-lte/dist/css/skins/skin-purple.css
cruds_adminlte/static/admin-lte/dist/css/skins/skin-purple.min.css
cruds_adminlte/static/admin-lte/dist/css/skins/skin-red-light.css
cruds_adminlte/static/admin-lte/dist/css/skins/skin-red-light.min.css
cruds_adminlte/static/admin-lte/dist/css/skins/skin-red.css
cruds_adminlte/static/admin-lte/dist/css/skins/skin-red.min.css
cruds_adminlte/static/admin-lte/dist/css/skins/skin-yellow-light.css
django_cruds_adminlte.egg-info/PKG-INFO
django_cruds_adminlte.egg-info/SOURCES.txt
django_cruds_adminlte.egg-info/dependency_links.txt
django_cruds_adminlte.egg-info/not-zip-safe
django_cruds_adminlte.egg-info/requires.txt
django_cruds_adminlte.egg-info/top_level.txt